gov_cli/__init__.py
gov_cli/gov_cli.py
gov_cli-1.0.dist-info/METADATA
gov_cli-1.0.dist-info/WHEEL
gov_cli-1.0.dist-info/entry_points.txt
gov_cli-1.0.dist-info/top_level.txt
gov_cli-1.0.dist-info/RECORD
