Metadata-Version: 2.1
Name: gov-cli
Version: 1.0
Summary: cardano-cli 
Home-page: https://github.com/cardanoapi/gov-cli
Author: Sudip Bhattarai
Author-email: sudip@sireto.io
License: UNKNOWN
Platform: UNKNOWN
Classifier: Programming Language :: Python :: 3
Classifier: License :: OSI Approved :: MIT License
Classifier: Operating System :: OS Independent
Requires-Python: >=3.0
